garminmaps/__init__.py
garminmaps/activities.py
garminmaps/garmin.py
garminmaps/mapping.py
garminmaps/tester.py
garminmaps/utils.py
garminmaps-0.0.8.dist-info/METADATA
garminmaps-0.0.8.dist-info/WHEEL
garminmaps-0.0.8.dist-info/licenses/LICENSE
garminmaps-0.0.8.dist-info/RECORD
