Metadata-Version: 2.3
Name: garminmaps
Version: 0.0.8
Summary: SDK for generating interactive leaflet.js maps from Garmin data.
Project-URL: Homepage, https://github.com/doorlay/garminmaps
Project-URL: Issues, https://github.com/doorlay/garminmaps/issues
Author-email: Nic Doorlay <ndoorlay@gmail.com>
License-File: LICENSE
Classifier: License :: OSI Approved :: MIT License
Classifier: Operating System :: OS Independent
Classifier: Programming Language :: Python :: 3
Requires-Python: >=3.8
Requires-Dist: folium==0.17.0
Requires-Dist: garminconnect==0.2.19
Requires-Dist: garth==0.4.46
Requires-Dist: gpxpy==1.6.2
Requires-Dist: pandas==2.2.2
Provides-Extra: dev
Requires-Dist: build==1.2.1; extra == 'dev'
Requires-Dist: ruff==0.5.3; extra == 'dev'
Requires-Dist: twine==5.1.1; extra == 'dev'
